LICENSE
MANIFEST.in
README.md
README.txt
setup.py
LiPD.egg-info/PKG-INFO
LiPD.egg-info/SOURCES.txt
LiPD.egg-info/dependency_links.txt
LiPD.egg-info/requires.txt
LiPD.egg-info/top_level.txt
docs/conf.py
docs/index.rst
docs/_build/html/.buildinfo
docs/_build/html/.nojekyll
docs/_build/html/genindex.html
docs/_build/html/index.html
docs/_build/html/objects.inv
docs/_build/html/py-modindex.html
docs/_build/html/search.html
docs/_build/html/searchindex.js
docs/_build/html/_sources/index.rst
docs/_build/html/_sources/index.rst.txt
docs/_build/html/_sources/source/lipd.rst
docs/_build/html/_sources/source/lipd.rst.txt
docs/_build/html/_sources/source/modules.rst
docs/_build/html/_sources/source/modules.rst.txt
docs/_build/html/_sources/source/readme.rst.txt
docs/_build/html/_static/ajax-loader.gif
docs/_build/html/_static/alabaster.css
docs/_build/html/_static/basic.css
docs/_build/html/_static/comment-bright.png
docs/_build/html/_static/comment-close.png
docs/_build/html/_static/comment.png
docs/_build/html/_static/custom.css
docs/_build/html/_static/doctools.js
docs/_build/html/_static/down-pressed.png
docs/_build/html/_static/down.png
docs/_build/html/_static/file.png
docs/_build/html/_static/jquery-3.1.0.js
docs/_build/html/_static/jquery.js
docs/_build/html/_static/minus.png
docs/_build/html/_static/plus.png
docs/_build/html/_static/pygments.css
docs/_build/html/_static/searchtools.js
docs/_build/html/_static/underscore-1.3.1.js
docs/_build/html/_static/underscore.js
docs/_build/html/_static/up-pressed.png
docs/_build/html/_static/up.png
docs/_build/html/_static/websupport.js
docs/_build/html/_static/css/badge_only.css
docs/_build/html/_static/css/theme.css
docs/_build/html/_static/fonts/Inconsolata-Bold.ttf
docs/_build/html/_static/fonts/Inconsolata-Regular.ttf
docs/_build/html/_static/fonts/Lato-Bold.ttf
docs/_build/html/_static/fonts/Lato-Regular.ttf
docs/_build/html/_static/fonts/RobotoSlab-Bold.ttf
docs/_build/html/_static/fonts/RobotoSlab-Regular.ttf
docs/_build/html/_static/fonts/fontawesome-webfont.eot
docs/_build/html/_static/fonts/fontawesome-webfont.svg
