Metadata-Version: 2.1
Name: LiPD
Version: 0.2.7.1
Summary: LiPD utilities to process, convert, and analyze data.
Home-page: https://github.com/nickmckay/LiPD-utilities
Author: C. Heiser
Author-email: heiser@nau.edu
License: GNU Public
Keywords: paleo R matlab python paleoclimatology linkedearth
Platform: UNKNOWN
